dalloriam/__init__.py
dalloriam/exceptions.py
dalloriam/authentication/__init__.py
dalloriam/authentication/user.py
dalloriam/data/__init__.py
dalloriam/data/combine.py
dalloriam/datahose/__init__.py
dalloriam/datahose/client.py
dalloriam/orc/__init__.py
dalloriam/orc/client.py
dalloriam/orc/error.py
dalloriam/orc/keyval.py
dalloriam/orc/task.py
dalloriam/system/__init__.py
dalloriam/system/path.py
tests/__init__.py
tests/authentication/__init__.py
tests/authentication/test_user.py
tests/filesystem/__init__.py
tests/filesystem/test_path.py
tests/mocks/__init__.py
tests/mocks/datastore.py
tests/mocks/location.py
dalloriam-0.5.2.dist-info/LICENSE
dalloriam-0.5.2.dist-info/METADATA
dalloriam-0.5.2.dist-info/WHEEL
dalloriam-0.5.2.dist-info/top_level.txt
dalloriam-0.5.2.dist-info/RECORD
