Metadata-Version: 2.1
Name: dalloriam
Version: 0.5.2
Summary: Personal standard library.
Home-page: https://github.com/dalloriam/python-stdlib
Author: William Dussault
Author-email: dalloriam@gmail.com
License: MIT
Platform: UNKNOWN
Requires-Dist: requests
Requires-Dist: sh
Requires-Dist: google-cloud-datastore
Requires-Dist: google-auth
